aws_cost_optimization_14/__init__.py
aws_cost_optimization_14/_cloudwatch_costing.py
aws_cost_optimization_14/_ec2_costing.py
aws_cost_optimization_14/_elb_costing.py
aws_cost_optimization_14/_kms_costing.py
aws_cost_optimization_14/_rds_costing.py
aws_cost_optimization_14/_ri_recommendations.py
aws_cost_optimization_14/_savings_plan.py
aws_cost_optimization_14/utils.py
aws_cost_optimization_14-0.2.13.dist-info/LICENCE
aws_cost_optimization_14-0.2.13.dist-info/METADATA
aws_cost_optimization_14-0.2.13.dist-info/WHEEL
aws_cost_optimization_14-0.2.13.dist-info/top_level.txt
aws_cost_optimization_14-0.2.13.dist-info/RECORD
