Metadata-Version: 2.1
Name: aws-cost-optimization-14
Version: 0.2.13
Summary: Provides AWS cost recommendations
Author-email: "dheeraj.banodha" <dheeraj.banodha@impetus.com>
Classifier: Programming Language :: Python :: 3
Classifier: Operating System :: OS Independent
Requires-Python: >=3.10
License-File: LICENCE
